{
  "logoType": "none",
  "logo": {
    "lucideIcon": "",
    "imagePath": "",
    "imageLink": ""
  },
  "logoScale": 3,
  "iconColorType": "default",
  "wordmark": "WELKOM LUIS",
  "customFont": "textFont",
  "fontSize": "8em",
  "fontColorType": "accentColor",
  "fontWeight": 900,
  "maxResults": 10,
  "showbookmarkedFiles": true,
  "showRecentFiles": false,
  "maxRecentFiles": 5,
  "storeRecentFile": true,
  "showPath": true,
  "selectionHighlight": "accentColor",
  "showShortcuts": true,
  "markdownOnly": false,
  "unresolvedLinks": false,
  "recentFilesStore": [
    {
      "filepath": "Generele informatie/Notes.md",
      "timestamp": 1758794930798
    },
    {
      "filepath": "Kanban Board/Notes/Stageverslag Lay-Out design.md",
      "timestamp": 1758794408722
    },
    {
      "filepath": "Kanban Board/Kanban board.md",
      "timestamp": 1758794399550
    },
    {
      "filepath": "Main Workspace.canvas",
      "timestamp": 1758789673780
    },
    {
      "filepath": "Kanban Board/Notes/Stage verslag Documentatie.md",
      "timestamp": 1758789645272
    }
  ],
  "bookmarkedFileStore": [
    {
      "filepath": "Main Workspace.canvas"
    },
    {
      "filepath": "Generele informatie/Notes.md"
    },
    {
      "filepath": "Kanban Board/Kanban board.md"
    }
  ],
  "searchDelay": 0,
  "replaceNewTabs": true,
  "newTabOnStart": true,
  "closePreviousSessionTabs": true,
  "omnisearch": true,
  "showOmnisearchExcerpt": true
}